[
  {
    "Source_link": "https://whatsapp.com/channel/0029Va5nZToFSAt56yKM0C1f",
    "Post_text": "images/image_Netflix_2025-05-26 11:59:19_1.gif",
    "Post_image": "C-C-C-CUBBIES!!!!!! GOOD MORNING GOOD AFTERNOON GOOD NIGHT!! ",
    "Post_time": "10:30 PM",
    "Post_reaction": "3,797",
    "Post_scraping_time": "2025-05-26 11:59:19"
  },
  {
    "Source_link": "https://whatsapp.com/channel/0029Va5nZToFSAt56yKM0C1f",
    "Post_text": "images/image_Netflix_2025-05-26 11:59:19_2.gif",
    "Post_image": "OK WHY WAS MY PROMPOSAL NOT THIS GOOD?????!!!! FEAR STREET: PROM QUEEN PREMIERES IN 2 DAYS!",
    "Post_time": "3:02 AM",
    "Post_reaction": "6,077",
    "Post_scraping_time": "2025-05-26 11:59:19"
  },
  {
    "Source_link": "https://whatsapp.com/channel/0029Va5nZToFSAt56yKM0C1f",
    "Post_text": "images/image_Netflix_2025-05-26 11:59:19_3.gif",
    "Post_image": "CUBBIES!!! GOOD MORNING GOOD AFTERNOON GOOD NIGHT ",
    "Post_time": "10:27 PM",
    "Post_reaction": "2,847",
    "Post_scraping_time": "2025-05-26 11:59:19"
  },
  {
    "Source_link": "https://whatsapp.com/channel/0029Va5nZToFSAt56yKM0C1f",
    "Post_text": "images/image_Netflix_2025-05-26 11:59:19_4.gif",
    "Post_image": "ROOOOLLLLLL CAAAAAALLLLLLLL",
    "Post_time": "3:59 AM",
    "Post_reaction": "570",
    "Post_scraping_time": "2025-05-26 11:59:20"
  },
  {
    "Source_link": "https://whatsapp.com/channel/0029Va5nZToFSAt56yKM0C1f",
    "Post_text": "images/image_Netflix_2025-05-26 11:59:20_5.gif",
    "Post_image": "CYA ON FINSTA  @netflix2",
    "Post_time": "Edited3:59 AM",
    "Post_reaction": "988",
    "Post_scraping_time": "2025-05-26 11:59:20"
  },
  {
    "Source_link": "https://whatsapp.com/channel/0029Va5nZToFSAt56yKM0C1f",
    "Post_text": "images/image_Netflix_2025-05-26 11:59:20_6.jpeg",
    "Post_image": "DONT BE SCARED CUB WE BELIEVE IN U!!! ️️️",
    "Post_time": "4:39 AM",
    "Post_reaction": "670",
    "Post_scraping_time": "2025-05-26 11:59:20"
  },
  {
    "Source_link": "https://whatsapp.com/channel/0029Va5nZToFSAt56yKM0C1f",
    "Post_text": "images/image_Netflix_2025-05-26 11:59:20_7.jpeg",
    "Post_image": "OMG IM CRYING ILY ",
    "Post_time": "4:40 AM",
    "Post_reaction": "672",
    "Post_scraping_time": "2025-05-26 11:59:20"
  },
  {
    "Source_link": "https://whatsapp.com/channel/0029Va5nZToFSAt56yKM0C1f",
    "Post_text": "images/image_Netflix_2025-05-26 11:59:20_8.jpeg",
    "Post_image": "HIIII CUBBIEEEE IM SO GOOD!!!! READY FOR FRIDAY! ",
    "Post_time": "4:40 AM",
    "Post_reaction": "743",
    "Post_scraping_time": "2025-05-26 11:59:20"
  },
  {
    "Source_link": "https://whatsapp.com/channel/0029Va5nZToFSAt56yKM0C1f",
    "Post_text": "images/image_Netflix_2025-05-26 11:59:20_9.jpeg",
    "Post_image": "SOUNDS LIKE A FUN WEEK!!! I FULLY SUPPORT UR REWATCH LIST CUB ",
    "Post_time": "4:41 AM",
    "Post_reaction": "762",
    "Post_scraping_time": "2025-05-26 11:59:20"
  },
  {
    "Source_link": "https://whatsapp.com/channel/0029Va5nZToFSAt56yKM0C1f",
    "Post_text": "images/image_Netflix_2025-05-26 11:59:20_10.jpeg",
    "Post_image": "HAPPY BIRTHDAY CUBBIE!!!! ",
    "Post_time": "4:42 AM",
    "Post_reaction": "963",
    "Post_scraping_time": "2025-05-26 11:59:20"
  },
  {
    "Source_link": "https://whatsapp.com/channel/0029Va5nZToFSAt56yKM0C1f",
    "Post_text": "images/image_Netflix_2025-05-26 11:59:20_11.jpeg",
    "Post_image": "NOOO WAAAAYYYY  AW SRY CUB IM SENDING U SUNSHINE FROM LA ",
    "Post_time": "4:43 AM",
    "Post_reaction": "938",
    "Post_scraping_time": "2025-05-26 11:59:20"
  },
  {
    "Source_link": "https://whatsapp.com/channel/0029Va5nZToFSAt56yKM0C1f",
    "Post_text": "images/image_Netflix_2025-05-26 11:59:20_12.jpeg",
    "Post_image": "",
    "Post_time": "4:44 AM",
    "Post_reaction": "1,093",
    "Post_scraping_time": "2025-05-26 11:59:20"
  },
  {
    "Source_link": "https://whatsapp.com/channel/0029Va5nZToFSAt56yKM0C1f",
    "Post_text": "images/image_Netflix_2025-05-26 11:59:20_13.jpeg",
    "Post_image": "OMG THERAPY IS LITERALLY THE BEST!!!  GOOD LUCK ",
    "Post_time": "4:44 AM",
    "Post_reaction": "1,235",
    "Post_scraping_time": "2025-05-26 11:59:20"
  },
  {
    "Source_link": "https://whatsapp.com/channel/0029Va5nZToFSAt56yKM0C1f",
    "Post_text": "images/image_Netflix_2025-05-26 11:59:20_14.jpeg",
    "Post_image": "DONT FORGET TO FLOSS  GOOD LUCK",
    "Post_time": "4:45 AM",
    "Post_reaction": "1,177",
    "Post_scraping_time": "2025-05-26 11:59:20"
  },
  {
    "Source_link": "https://whatsapp.com/channel/0029Va5nZToFSAt56yKM0C1f",
    "Post_text": "images/image_Netflix_2025-05-26 11:59:21_15.jpeg",
    "Post_image": "OMG I LOVE ARCANE!!!! ",
    "Post_time": "4:46 AM",
    "Post_reaction": "2,541",
    "Post_scraping_time": "2025-05-26 11:59:21"
  },
  {
    "Source_link": "https://whatsapp.com/channel/0029Va5nZToFSAt56yKM0C1f",
    "Post_text": "images/image_Netflix_2025-05-26 11:59:21_16.gif",
    "Post_image": "are they flirting w me…???",
    "Post_time": "7:28 AM",
    "Post_reaction": "6,175",
    "Post_scraping_time": "2025-05-26 11:59:21"
  },
  {
    "Source_link": "https://whatsapp.com/channel/0029Va5nZToFSAt56yKM0C1f",
    "Post_text": "images/image_Netflix_2025-05-26 11:59:21_17.gif",
    "Post_image": "GOOD MORNING GOOD AFTERNOON GOOD NIGHT ",
    "Post_time": "10:23 PM",
    "Post_reaction": "2,267",
    "Post_scraping_time": "2025-05-26 11:59:21"
  },
  {
    "Source_link": "https://whatsapp.com/channel/0029Va5nZToFSAt56yKM0C1f",
    "Post_text": "images/image_Netflix_2025-05-26 11:59:21_18.gif",
    "Post_image": "CUBS WHOS EXCITED FOR K-POP DEMON HUNTER????? I HAVE A SURPRISE FOR YOUUUUU",
    "Post_time": "11:10 PM",
    "Post_reaction": "1,798",
    "Post_scraping_time": "2025-05-26 11:59:21"
  },
  {
    "Source_link": "https://whatsapp.com/channel/0029Va5nZToFSAt56yKM0C1f",
    "Post_text": "images/image_Netflix_2025-05-26 11:59:21_19.gif",
    "Post_image": "TWICE RECORDED A VIDEO FOR US!!!!! RAISE UR HAND IF UR GONNA JOIN THE TIKTOK DANCE CHALLENGE            ",
    "Post_time": "11:13 PM",
    "Post_reaction": "10,203",
    "Post_scraping_time": "2025-05-26 11:59:21"
  }
]